drasi/__init__.py
drasi/reaction/__init__.py
drasi/reaction/logger.py
drasi/reaction/models/BootstrapCompletedSignal.py
drasi/reaction/models/BootstrapStartedSignal.py
drasi/reaction/models/ChangeEvent.py
drasi/reaction/models/ControlEvent.py
drasi/reaction/models/ControlSignal.py
drasi/reaction/models/Data.py
drasi/reaction/models/DeletedSignal.py
drasi/reaction/models/Header.py
drasi/reaction/models/HeaderItem.py
drasi/reaction/models/ResultEvent.py
drasi/reaction/models/RunningSignal.py
drasi/reaction/models/StoppedSignal.py
drasi/reaction/models/UpdatePayload.py
drasi/reaction/models/Versions.py
drasi/reaction/models/ViewItem.py
drasi/reaction/models/__init__.py
drasi/reaction/sdk.py
drasi/reaction/utils.py
drasi_reaction_sdk-0.1.1a0.dist-info/METADATA
drasi_reaction_sdk-0.1.1a0.dist-info/WHEEL
drasi_reaction_sdk-0.1.1a0.dist-info/RECORD
