Metadata-Version: 2.1
Name: drasi-reaction-sdk
Version: 0.1.1a0
Summary: Reaction SDK for Project Drasi
Home-page: https://drasi.io
License: Apache-2.0
Author: Steve Russo
Author-email: 64294847+sjrusso8@users.noreply.github.com
Requires-Python: >=3.10,<4.0
Classifier: License :: OSI Approved :: Apache Software License
Classifier: Programming Language :: Python :: 3
Classifier: Programming Language :: Python :: 3.10
Classifier: Programming Language :: Python :: 3.11
Classifier: Programming Language :: Python :: 3.12
Requires-Dist: PyYAML (==6.0.2)
Requires-Dist: dapr (>=1.14.0,<2.0.0)
Requires-Dist: dapr-ext-fastapi (>=1.14.0,<2.0.0)
Requires-Dist: fastapi (>=0.115.4,<0.116.0)
Requires-Dist: pydantic (>=2.10.0,<3.0.0)
Project-URL: Repository, https://github.com/drasi-project/drasi-platform
